pwdsafe/__init__.py
pwdsafe-1.0.0.dist-info/WHEEL
pwdsafe-1.0.0.dist-info/METADATA
pwdsafe-1.0.0.dist-info/RECORD
